thonnycontrib/AIChatView.py
thonnycontrib/__init__.py
thonny_chatbot_plugin-0.1.7.dist-info/METADATA
thonny_chatbot_plugin-0.1.7.dist-info/WHEEL
thonny_chatbot_plugin-0.1.7.dist-info/top_level.txt
thonny_chatbot_plugin-0.1.7.dist-info/RECORD
