Metadata-Version: 2.4
Name: thonny-chatbot-plugin
Version: 0.1.7
Summary: A Thonny IDE plugin that provides an AI chat interface.
Author-email: pondahai <dahai.pon@gmail.com>
Maintainer-email: pondahai <dahai.pon@gmail.com>
License: MIT
Project-URL: Homepage, https://github.com/pondahai/thonny_chatbot_plugin
Project-URL: Bug Tracker, https://github.com/pondahai/thonny_chatbot_plugin/issues
Keywords: thonny,plugin,ai,assistant,llm,openai
Classifier: Development Status :: 3 - Alpha
Classifier: Environment :: Plugins
Classifier: Intended Audience :: Developers
Classifier: Intended Audience :: Education
Classifier: License :: OSI Approved :: MIT License
Classifier: Natural Language :: English
Classifier: Operating System :: OS Independent
Classifier: Programming Language :: Python :: 3
Classifier: Programming Language :: Python :: 3.8
Classifier: Programming Language :: Python :: 3.9
Classifier: Programming Language :: Python :: 3.10
Classifier: Programming Language :: Python :: 3.11
Classifier: Programming Language :: Python :: 3.12
Classifier: Topic :: Education
Classifier: Topic :: Software Development :: Debuggers
Classifier: Topic :: Text Editors :: Integrated Development Environments (IDE)
Requires-Python: >=3.8
Requires-Dist: requests>=2.20.0
